openmsistream/__init__.py
openmsistream/data_file_io/__init__.py
openmsistream/data_file_io/config.py
openmsistream/data_file_io/utilities.py
openmsistream/data_file_io/actor/__init__.py
openmsistream/data_file_io/actor/data_file_chunk_handlers.py
openmsistream/data_file_io/actor/data_file_download_directory.py
openmsistream/data_file_io/actor/data_file_stream_handler.py
openmsistream/data_file_io/actor/data_file_stream_processor.py
openmsistream/data_file_io/actor/data_file_stream_reproducer.py
openmsistream/data_file_io/actor/data_file_upload_directory.py
openmsistream/data_file_io/actor/file_registry/__init__.py
openmsistream/data_file_io/actor/file_registry/producer_file_registry.py
openmsistream/data_file_io/actor/file_registry/stream_handler_registries.py
openmsistream/data_file_io/entity/__init__.py
openmsistream/data_file_io/entity/data_file.py
openmsistream/data_file_io/entity/data_file_chunk.py
openmsistream/data_file_io/entity/data_file_directory.py
openmsistream/data_file_io/entity/download_data_file.py
openmsistream/data_file_io/entity/reproducer_message.py
openmsistream/data_file_io/entity/upload_data_file.py
openmsistream/data_file_io/entity/upload_directory_event_handler.py
openmsistream/girder/__init__.py
openmsistream/girder/girder_upload_stream_processor.py
openmsistream/kafka_wrapper/__init__.py
openmsistream/kafka_wrapper/config_file_parser.py
openmsistream/kafka_wrapper/consumer_and_producer_group.py
openmsistream/kafka_wrapper/consumer_group.py
openmsistream/kafka_wrapper/controlled_message_processor.py
openmsistream/kafka_wrapper/controlled_message_reproducer.py
openmsistream/kafka_wrapper/openmsistream_consumer.py
openmsistream/kafka_wrapper/openmsistream_kafka_crypto.py
openmsistream/kafka_wrapper/openmsistream_producer.py
openmsistream/kafka_wrapper/producer_group.py
openmsistream/kafka_wrapper/producible.py
openmsistream/kafka_wrapper/serialization.py
openmsistream/kafka_wrapper/utilities.py
openmsistream-1.8.3.6.dist-info/licenses/LICENSE
openmsistream-1.8.3.6.dist-info/METADATA
openmsistream-1.8.3.6.dist-info/WHEEL
openmsistream-1.8.3.6.dist-info/entry_points.txt
openmsistream-1.8.3.6.dist-info/top_level.txt
openmsistream-1.8.3.6.dist-info/RECORD
