Metadata-Version: 2.4
Name: openmsistream
Version: 1.8.3.6
Summary: Python applications for materials data streaming using Apache Kafka. Developed for Open MSI (NSF DMREF award #1921959)
Home-page: https://github.com/openmsi/openmsistream
Download-URL: https://github.com/openmsi/openmsistream/archive/refs/tags/v1.8.3.6.tar.gz
Author: OpenMSIStream
Author-email: openmsistream@gmail.com
License: GNU GPLv3
Keywords: data_streaming,stream_processing,apache_kafka,materials,data_science
Classifier: Programming Language :: Python :: 3.7
Classifier: Programming Language :: Python :: 3.9
Classifier: License :: OSI Approved :: GNU General Public License v3 (GPLv3)
Classifier: Operating System :: OS Independent
Requires-Python: >=3.7,<3.12
License-File: LICENSE
Requires-Dist: atomicwrites>=1.4.1
Requires-Dist: boto3>=1.26.84
Requires-Dist: confluent-kafka>=2.0.2
Requires-Dist: girder-client>=3.1.20
Requires-Dist: kafka-python>=2.0.2
Requires-Dist: kafkacrypto>=0.9.10.3
Requires-Dist: matplotlib
Requires-Dist: methodtools
Requires-Dist: msgpack
Requires-Dist: openmsitoolbox>=1.2.4
Requires-Dist: watchdog>=3.0.0
Provides-Extra: test
Requires-Dist: beautifulsoup4; extra == "test"
Requires-Dist: black; extra == "test"
Requires-Dist: docker; extra == "test"
Requires-Dist: gitpython; extra == "test"
Requires-Dist: lxml; extra == "test"
Requires-Dist: marko[toc]==1.3.0; extra == "test"
Requires-Dist: packaging; extra == "test"
Requires-Dist: pyflakes>=3.0.1; extra == "test"
Requires-Dist: pylint>=2.16.3; extra == "test"
Requires-Dist: requests; extra == "test"
Requires-Dist: responses; extra == "test"
Requires-Dist: tempenv>=2.0.0; extra == "test"
Requires-Dist: unittest-xml-reporting; extra == "test"
Provides-Extra: docs
Requires-Dist: sphinx>=6.1.3; extra == "docs"
Requires-Dist: sphinx_rtd_theme>=1.2.0; extra == "docs"
Provides-Extra: dev
Requires-Dist: twine; extra == "dev"
Provides-Extra: all
Requires-Dist: beautifulsoup4; extra == "all"
Requires-Dist: black; extra == "all"
Requires-Dist: docker; extra == "all"
Requires-Dist: gitpython; extra == "all"
Requires-Dist: lxml; extra == "all"
Requires-Dist: marko[toc]==1.3.0; extra == "all"
Requires-Dist: packaging; extra == "all"
Requires-Dist: pyflakes>=3.0.1; extra == "all"
Requires-Dist: pylint>=2.16.3; extra == "all"
Requires-Dist: requests; extra == "all"
Requires-Dist: responses; extra == "all"
Requires-Dist: tempenv>=2.0.0; extra == "all"
Requires-Dist: unittest-xml-reporting; extra == "all"
Requires-Dist: sphinx>=6.1.3; extra == "all"
Requires-Dist: sphinx_rtd_theme>=1.2.0; extra == "all"
Requires-Dist: twine; extra == "all"
Dynamic: author
Dynamic: author-email
Dynamic: classifier
Dynamic: description
Dynamic: description-content-type
Dynamic: download-url
Dynamic: home-page
Dynamic: keywords
Dynamic: license
Dynamic: license-file
Dynamic: provides-extra
Dynamic: requires-dist
Dynamic: requires-python
Dynamic: summary
